[
  {
    "question": "Jak w Lua tworzysz zmienna?",
    "answers": [
      { "answer": "nazwa = wartosc", "is_correct": true },
      { "answer": "var nazwa = wartosc", "is_correct": false },
      { "answer": "nazwa := wartosc", "is_correct": false }
    ]
  },
  {
    "question": "Jaki typ ma zmienna: a = 1.2 ?",
    "answers": [
      { "answer": "Liczba zmiennoprzecinkowa", "is_correct": true },
      { "answer": "Zmienna znakowa", "is_correct": false },
      { "answer": "Tablica", "is_correct": false }
    ]
  },
  {
    "question": "Jak zapiszesz tekst w Lua?",
    "answers": [
      { "answer": "\"tekst\"", "is_correct": true },
      { "answer": "tekst()", "is_correct": false },
      { "answer": "[tekst]", "is_correct": false }
    ]
  },
  {
    "question": "Jak utworzysz pusta tablice?",
    "answers": [
      { "answer": "tab = {}", "is_correct": true },
      { "answer": "tab = []", "is_correct": false },
      { "answer": "tab = ()", "is_correct": false }
    ]
  },
  {
    "question": "Prawda czy falsz: true to prawda.",
    "answers": [
      { "answer": "Prawda", "is_correct": true },
      { "answer": "Falsz", "is_correct": false }
    ]
  },
  {
    "question": "Jaki operator znaczy \"rowne\"?",
    "answers": [
      { "answer": "==", "is_correct": true },
      { "answer": "=", "is_correct": false },
      { "answer": "!=", "is_correct": false }
    ]
  },
  {
    "question": "Jaki operator znaczy \"rozne\"?",
    "answers": [
      { "answer": "~=", "is_correct": true },
      { "answer": "!=", "is_correct": false },
      { "answer": "==", "is_correct": false }
    ]
  },
  {
    "question": "Jak zaczyna sie if w Lua?",
    "answers": [
      { "answer": "if warunek then", "is_correct": true },
      { "answer": "if (warunek) {", "is_correct": false },
      { "answer": "if warunek:", "is_correct": false }
    ]
  },
  {
    "question": "Jak zamykasz blok if?",
    "answers": [
      { "answer": "end", "is_correct": true },
      { "answer": "}", "is_correct": false },
      { "answer": "stop", "is_correct": false }
    ]
  },
  {
    "question": "Jak wywolac funkcje test()?",
    "answers": [
      { "answer": "test()", "is_correct": true },
      { "answer": "call test", "is_correct": false },
      { "answer": "test[]", "is_correct": false }
    ]
  }
]
